mder/__init__.py
mder-1.0.2.dist-info/METADATA
mder-1.0.2.dist-info/WHEEL
mder-1.0.2.dist-info/top_level.txt
mder-1.0.2.dist-info/RECORD
