Metadata-Version: 2.1
Name: mder
Version: 1.0.2
Summary: A multithreading m3u8 download module for python, and the number of threads can decide by yourself; Convert .m3u8 file to .mp4 file; Supporting redownload.
Home-page: https://github.com/walkureHHH/M3u8_Downloader
Author: walkureHHH
Author-email: 1779599839@qq.com
License: UNKNOWN
Platform: UNKNOWN
Classifier: Programming Language :: Python :: 3
Classifier: License :: OSI Approved :: MIT License
Classifier: Operating System :: OS Independent
Requires-Dist: requests
Requires-Dist: tqdm
